dpu_utils/__init__.py
dpu_utils/py.typed
dpu_utils/codeutils/__init__.py
dpu_utils/codeutils/filesuffix.py
dpu_utils/codeutils/identifiersplitting.py
dpu_utils/codeutils/text.py
dpu_utils/codeutils/deduplication/__init__.py
dpu_utils/codeutils/deduplication/deduplication.py
dpu_utils/codeutils/deduplication/deduplicationcli
dpu_utils/codeutils/keywords/__init__.py
dpu_utils/codeutils/keywords/c.txt
dpu_utils/codeutils/keywords/cpp.txt
dpu_utils/codeutils/keywords/csharp.txt
dpu_utils/codeutils/keywords/go.txt
dpu_utils/codeutils/keywords/java.txt
dpu_utils/codeutils/keywords/javascript.txt
dpu_utils/codeutils/keywords/keywordlist.py
dpu_utils/codeutils/keywords/php.txt
dpu_utils/codeutils/keywords/ruby.txt
dpu_utils/codeutils/keywords/typescript.txt
dpu_utils/codeutils/lattice/__init__.py
dpu_utils/codeutils/lattice/csharplattice.py
dpu_utils/codeutils/lattice/lattice.py
dpu_utils/codeutils/treesitter/__init__.py
dpu_utils/codeutils/treesitter/parser.py
dpu_utils/mlutils/__init__.py
dpu_utils/mlutils/bpevocabulary.py
dpu_utils/mlutils/chartensorizer.py
dpu_utils/mlutils/vocabulary.py
dpu_utils/ptutils/__init__.py
dpu_utils/ptutils/basecomponent.py
dpu_utils/ptutils/componenttrainer.py
dpu_utils/tf2utils/__init__.py
dpu_utils/tf2utils/activation.py
dpu_utils/tf2utils/constants.py
dpu_utils/tf2utils/mlp.py
dpu_utils/tf2utils/unsorted_segment_ops.py
dpu_utils/tfmodels/__init__.py
dpu_utils/tfmodels/asyncgnn.py
dpu_utils/tfmodels/sparsegnn.py
dpu_utils/tfutils/__init__.py
dpu_utils/tfutils/activation.py
dpu_utils/tfutils/gradratiologgingoptimizer.py
dpu_utils/tfutils/pick_indices.py
dpu_utils/tfutils/tfvariablesaver.py
dpu_utils/tfutils/unsortedsegmentops.py
dpu_utils/utils/__init__.py
dpu_utils/utils/chunkwriter.py
dpu_utils/utils/dataloading.py
dpu_utils/utils/debughelper.py
dpu_utils/utils/gitlog.py
dpu_utils/utils/iterators.py
dpu_utils/utils/msgpackloading.py
dpu_utils/utils/richpath.py
dpu_utils-0.6.1.data/scripts/deduplicationcli
tests/__init__.py
dpu_utils-0.6.1.dist-info/METADATA
dpu_utils-0.6.1.dist-info/WHEEL
dpu_utils-0.6.1.dist-info/top_level.txt
dpu_utils-0.6.1.dist-info/RECORD
