Metadata-Version: 2.1
Name: dpu-utils
Version: 0.6.1
Summary: Python utilities used by Deep Procedural Intelligence
Home-page: https://github.com/microsoft/dpu-utils
Author: Deep Procedural Intelligence
License: MIT
Platform: UNKNOWN
Requires-Python: >=3.6.1
Requires-Dist: azure-storage-blob
Requires-Dist: azure-identity
Requires-Dist: numpy
Requires-Dist: docopt
Requires-Dist: tqdm
Requires-Dist: SetSimilaritySearch
Requires-Dist: sentencepiece
Requires-Dist: cffi
Requires-Dist: regex
